pyblackjack/__init__.py
pyblackjack/__main__.py
pyblackjack/__version__.py
pyblackjack/controller.py
pyblackjack/model.py
pyblackjack/py.typed
pyblackjack/utils.py
pyblackjack/views/__init__.py
pyblackjack/views/_abc.py
pyblackjack/views/boss.py
pyblackjack/views/terminal.py
pyblackjack-0.6.0b1.dist-info/LICENSE
pyblackjack-0.6.0b1.dist-info/METADATA
pyblackjack-0.6.0b1.dist-info/WHEEL
pyblackjack-0.6.0b1.dist-info/entry_points.txt
pyblackjack-0.6.0b1.dist-info/top_level.txt
pyblackjack-0.6.0b1.dist-info/RECORD
