Metadata-Version: 2.2
Name: pyblackjack
Version: 0.6.0b1
Summary: Simple terminal-based blackjack game
Author-email: Jonathan Goble <jcgoble3@gmail.com>
License: MIT license
Project-URL: Home, https://gitlab.com/jgoble/blackjack
Keywords: game,blackjack
Classifier: Development Status :: 3 - Alpha
Classifier: Environment :: Console
Classifier: License :: OSI Approved :: MIT License
Classifier: Natural Language :: English
Classifier: Operating System :: OS Independent
Classifier: Programming Language :: Python :: 3.10
Classifier: Programming Language :: Python :: 3.11
Classifier: Programming Language :: Python :: 3.12
Classifier: Programming Language :: Python :: 3.13
Classifier: Topic :: Games/Entertainment
Requires-Python: >=3.10
License-File: LICENSE
Requires-Dist: blessed==1.20.0
Requires-Dist: typing_extensions<5,>=4.4.0
